simpledeco/__init__.py
simpledeco/utils.py
SimpleDeco-0.0.3.dist-info/LICENSE
SimpleDeco-0.0.3.dist-info/METADATA
SimpleDeco-0.0.3.dist-info/WHEEL
SimpleDeco-0.0.3.dist-info/top_level.txt
SimpleDeco-0.0.3.dist-info/RECORD
