Metadata-Version: 2.1
Name: SimpleDeco
Version: 0.0.3
Summary: Decorators without nested functions
Home-page: https://github.com/tm-a-t/SimpleDeco
Author: Artyom Ivanov
Author-email: a@tmat.me
License: UNKNOWN
Platform: UNKNOWN
Classifier: Programming Language :: Python :: 3
Classifier: License :: OSI Approved :: MIT License
Classifier: Operating System :: OS Independent
Requires-Python: >=3.9
License-File: LICENSE
